{
  "entity": "Burkina Faso",
  "entity_slug": "burkina-faso",
  "iso_code": "BF",
  "continent": "africa",
  "angle": "culture",
  "title": "Burkina Faso Culture - Food, Traditions & Etiquette",
  "content": "[SECTION] Cultural Identity [/SECTION]\nBurkina Faso's culture is a rich tapestry of over 60 ethnic groups, with the Mossi, Fulani, and Gourmanché being the largest. The country's cultural identity is defined by its strong sense of community, respect for tradition, and vibrant cultural expression. The Mossi people, who make up around 50% of the population, have had a significant influence on the country's culture, with their traditions and customs being widely practiced. The official language, French, is a legacy of the country's colonial past, but many local languages are also spoken, including Moore, Dioula, and Fulfulde.\n\nThe country's cultural makeup is also influenced by its Islamic and Christian heritage, with around 60% of the population practicing Islam and 20% practicing Christianity. This blend of traditional and modern influences is reflected in the country's art, music, and literature. The Burkinabé people are known for their warm hospitality and welcoming nature, with visitors often being greeted with a smile and a handshake. The concept of **teranga**, or hospitality, is deeply ingrained in Burkinabé culture, with visitors being treated as honored guests.\n\nThe country's cultural identity is also shaped by its history, with the ancient kingdoms of the Mossi and Gourmanché having played a significant role in shaping the country's traditions and customs. The country's cultural heritage is also reflected in its many museums, cultural centers, and historical sites, including the **Manéga Museum**, which showcases the country's rich cultural history.\n\n[SECTION] Food & Cuisine [/SECTION]\n| Dish | Type | Description | Must-Try? |\n| --- | --- | --- | --- |\n| Poulet bicyclette | Chicken dish | Grilled chicken served with onions, tomatoes, and peppers | Yes |\n| Riz gras | Rice dish | A flavorful rice dish made with meat, vegetables, and spices | Yes |\n| Mafé | Stew | A rich and flavorful stew made with meat, vegetables, and peanuts | Yes |\n| Thiakry | Dessert | A sweet and creamy dessert made with yogurt, millet, and sugar | Yes |\n| Tô | Traditional dish | A thick corn paste served with a sauce made from vegetables and meat | Yes |\n| Yassa | Chicken dish | Grilled chicken marinated in a spicy sauce made with onions, peppers, and spices | Yes |\n| Bouillie | Porridge | A thick and nutritious porridge made from millet or corn flour | No |\n| Jus de baobab | Drink | A sweet and refreshing drink made from the fruit of the baobab tree | Yes |\n\nEating customs in Burkina Faso are centered around community and sharing, with meals often being served in a communal setting. Mealtimes are seen as opportunities to bond with family and friends, and visitors are often invited to join in. The country's food culture is also influenced by its many ethnic groups, with each group having its own unique culinary traditions. **Fufu**, a staple dish made from boiled and pounded cassava or yams, is a popular accompaniment to many meals.\n\n[SECTION] Traditions & Festivals [/SECTION]\n| Festival/Tradition | When | What It Is |\n| --- | --- | --- |\n| Pan-African Film and Television Festival of Ouagadougou (FESPACO) | February/March | A biennial festival celebrating African film and television |\n| International Arts and Crafts Fair (SIAO) | October/November | A biennial fair showcasing the country's rich cultural heritage |\n| Festival of Masks | December | A colorful festival featuring traditional masks and dances |\n| Eid al-Fitr | Variable | A celebration marking the end of Ramadan |\n| Christmas | December 25 | A celebration marking the birth of Jesus Christ |\n| Independence Day | August 5 | A celebration marking the country's independence from France |\n\n[SECTION] Etiquette: Do's and Don'ts [/SECTION]\n**Do:**\n- Respect local customs and traditions, particularly when visiting rural areas\n- Learn a few basic phrases in the local language, such as **bonjour** (hello) and **merci** (thank you)\n- Remove your shoes when entering a mosque or a traditional home\n- Use your right hand when eating or giving/receiving something\n- Dress modestly and avoid revealing clothing\n- Show respect to elders and those in positions of authority\n\n**Don't:**\n- Don't point with your left hand, as this is considered rude\n- Don't eat with your left hand, as this is also considered rude\n- Don't take pictures of people without their permission, particularly in rural areas\n- Don't discuss sensitive topics, such as politics or religion, in public\n- Don't show public displays of affection, as this is generally frowned upon\n- Don't litter or dispose of waste in public areas\n\n[SECTION] Arts & Music [/SECTION]\n- The country is known for its rich tradition of **balafon** music, a type of xylophone music that is played during traditional ceremonies and celebrations\n- The **kora**, a 21-stringed instrument, is also a popular instrument in Burkinabé music\n- **Gnawa** music, a type of music that originated in Morocco, is also popular in Burkina Faso\n- The country has a thriving **film industry**, with many local filmmakers producing films that showcase the country's culture and traditions\n- **Literature** is also an important part of Burkinabé culture, with many local authors writing about the country's history, culture, and traditions\n\n[SECTION] Useful Phrases [/SECTION]\n| English | Local Language | Pronunciation |\n| --- | --- | --- |\n| Hello | Bonjour | Bone-jour |\n| Thank you | Merci | Mur-see |\n| Please | S'il vous plaît | See voo play |\n| Yes / No | Oui / Non | Wee / Noh |\n| How much? | Combien ça coûte? | Kohm-byeen sah koo-tay |\n| Goodbye | Au revoir | Oh reh-vwahr |\n| I don't understand | Je ne comprends pas | Zhuh nuh kohm-prehnd pah |\n| Where is...? | Où est...? | Oo eh... |\n| I'm lost | Je suis perdu(e) | Zhuh swee pehr-doo(ay) |\n| Help! | Au secours! | Oh seh-koor |",
  "word_count": 1003,
  "generated_date": "2026-02-12T04:36:27.041812"
}