{
  "entity": "Angola",
  "entity_slug": "angola",
  "iso_code": "AO",
  "continent": "africa",
  "angle": "cost-transportation",
  "title": "Transportation Costs in Angola",
  "content": "The cost of transportation in Angola can vary greatly depending on the mode of transport, with a monthly transit pass costing around $10-$20 USD, while a taxi start rate can range from $5-$10 USD.\n\n[FACTBOX]\nMonthly Transit Pass: ($15 USD)\nTaxi Start Rate: ($5 USD)\nFuel (per liter): ($1.20 USD)\nRide-Hailing Available: (Yes — apps like Taxify and Uber)\nCurrency: AOA\n[/FACTBOX]\n\n[SECTION] Getting Around Overview [/SECTION]\nAngola has a diverse range of transportation modes, including buses, taxis, and ride-hailing services. The quality of public transit varies greatly between cities, with Luanda having a more developed system than other parts of the country. Most people in Angola get around using **minibuses** or **shared taxis**, which are often overcrowded and unreliable. However, these services are generally affordable and can be a good option for short distances.\n\nIn larger cities like Luanda, there are also **city buses** that operate on fixed routes, providing a more reliable and comfortable option for commuters. Additionally, **ride-hailing apps** like Taxify and Uber are available in some cities, offering a convenient and relatively affordable way to get around. However, the availability and quality of these services can vary greatly depending on the location and time of day.\n\n[SECTION] Public Transportation [/SECTION]\n[TABLE]\n| Transport Type | Single Fare (USD) | Monthly Pass (USD) | Notes |\n| --- | --- | --- | --- |\n| City Bus | $0.50-$1.00 | $10-$20 | Limited coverage, unreliable schedules |\n| Metro / Subway | N/A | N/A | Not available in Angola |\n| Minibus / Shared Taxi | $0.50-$1.50 | N/A | Overcrowded, unreliable, but affordable |\n| Commuter Train | $1.00-$2.00 | $20-$50 | Limited routes, mostly used for cargo transport |\n[/TABLE]\n\n[SECTION] Taxi & Ride-Hailing [/SECTION]\n[TABLE]\n| Service | Base Fare (USD) | Per km (USD) | Typical City Ride (USD) | Notes |\n| --- | --- | --- | --- | --- |\n| Metered Taxi | $5.00 | $1.00 | $10-$20 | Can be expensive, negotiate fare before ride |\n| Ride-Hailing App | $2.00 | $0.50 | $5-$10 | Available in some cities, convenient and affordable |\n| Airport Transfer | N/A | N/A | $20-$50 | To city center, can be expensive |\n[/TABLE]\n\n[SECTION] Fuel & Driving Costs [/SECTION]\n[TABLE]\n| Item | Cost (USD) | Notes |\n| --- | --- | --- |\n| Gasoline (per liter) | $1.20 | Can vary depending on location and availability |\n| Diesel (per liter) | $1.00 | Used mostly for cargo transport and generators |\n| Car Rental (per day) | $50-$100 | Economy car, can be expensive and hard to find |\n| Parking (per hour, city) | $1.00-$2.00 | Limited parking options, can be expensive |\n| Toll Roads (typical) | $5.00-$10.00 | Limited toll roads, mostly used for cargo transport |\n[/TABLE]\n\n[SECTION] Intercity & Long-Distance [/SECTION]\n[TABLE]\n| Route Type | Cost Range (USD) | Notes |\n| --- | --- | --- |\n| Intercity Bus (4-5 hrs) | $10-$30 | Can be uncomfortable and unreliable |\n| Domestic Flight | $100-$300 | Typical route, can be expensive |\n| Train (long-distance) | $20-$50 | Limited routes, mostly used for cargo transport |\n[/TABLE]\n\n[SECTION] Transport Tips [/SECTION]\n- Use **ride-hailing apps** like Taxify and Uber for a convenient and relatively affordable way to get around cities.\n- Negotiate **taxi fares** before starting your ride to avoid overcharging.\n- Be prepared for **traffic congestion** and long travel times, especially in larger cities.\n- Use **minibuses** or **shared taxis** for short distances and affordable fares.\n- Consider **car rental** options for long-distance travel, but be aware of the costs and limited availability.\n- Always **check the currency exchange rate** before traveling to get the best value for your money.",
  "word_count": 636,
  "generated_date": "2026-02-17T09:08:33.077156"
}