{
  "entity": "India",
  "entity_slug": "india",
  "iso_code": "IN",
  "continent": "asia",
  "angle": "geography",
  "title": "Lucknow Geography - Location, Terrain & Climate",
  "content": "Lucknow is a city located in the northern part of India, in the state of Uttar Pradesh, and is known for its rich cultural heritage and historical significance.\n\n[FACTBOX]\nLand Area: 2,528 km², about the size of the state of Rhode Island\nHighest Point: Malwa Plateau, 200-500 meters\nLowest Point: Ganges River Valley, 100-200 meters\nCoastline: landlocked\nBorders: \nClimate Type: subtropical\n[/FACTBOX]\n\n[SECTION] Location & Borders [/SECTION]\nLucknow is situated in the heart of the Indo-Gangetic Plain, which is one of the most fertile and densely populated regions in the world. The city is located approximately 500 kilometers southeast of New Delhi, the capital city of India, and is surrounded by several districts, including Unnao, Rae Bareli, and Barabanki. Lucknow is a landlocked city, with no direct access to the sea, and is bordered by the Ganges River to the east and the Yamuna River to the west.\n\nThe city's strategic location has made it an important center of trade and commerce for centuries, with several major highways and railroads connecting it to other parts of the country. Lucknow is also a major cultural and educational hub, with several prestigious universities and research institutions, including the University of Lucknow and the Indian Institute of Management Lucknow. The city's proximity to the Himalayan Mountains and the Ganges River has also made it a popular destination for tourists and pilgrims, with several nearby attractions, including the Taj Mahal and the city of Varanasi.\n\n[SECTION] Terrain & Landscape [/SECTION]\nThe terrain of Lucknow is characterized by a flat to gently sloping plain, with an average elevation of around 120 meters above sea level. The city is situated in the Ganges River Valley, which is one of the most fertile and densely populated regions in the world. The soil is rich and fertile, making it suitable for agriculture, and the region is known for its production of crops such as wheat, rice, and sugarcane. The city's landscape is also dotted with several lakes, rivers, and canals, including the Gomti River, which flows through the heart of the city and provides a source of water for irrigation and drinking.\n\nThe city's terrain is also marked by several small hills and ridges, including the Malwa Plateau, which is located to the south of the city. The plateau is a relatively elevated region, with an average elevation of around 200-500 meters above sea level, and is known for its scenic beauty and rich biodiversity. The region is also home to several forests, including the Lucknow Forest Division, which is a protected area that covers an area of over 100 square kilometers. The forest is home to several species of trees, including teak, sal, and pine, as well as several species of wildlife, including deer, monkeys, and birds.\n\nThe city's landscape is also influenced by its rich cultural heritage, with several historic buildings, monuments, and gardens that reflect its rich history and architecture. The city is home to several Mughal-era monuments, including the Bara Imambara and the Chhota Imambara, which are known for their intricate architecture and beautiful gardens. The city is also home to several British-era buildings, including the Lucknow Residency, which is a historic building that dates back to the 18th century and is now a museum.\n\n[SECTION] Terrain & Landscape [/SECTION] continued\nIn addition to its natural beauty, Lucknow is also known for its rich cultural landscape, with several festivals and events that are celebrated throughout the year. The city is home to several historic mosques, temples, and churches, including the Asafi Imambara, which is one of the largest mosques in India. The city is also home to several historic gardens, including the Lohia Park, which is a beautiful park that covers an area of over 30 acres and is known for its scenic beauty and peaceful atmosphere.\n\n[SECTION] Climate By Season [/SECTION]\n[TABLE]\n| Season | Months | Temperature Range | Rainfall | Conditions |\n| --- | --- | --- | --- | --- |\n| Winter | December to February | 10-20°C | low | cool and dry |\n| Spring | March to May | 20-30°C | moderate | warm and humid |\n| Summer | June to August | 30-40°C | high | hot and humid |\n| Monsoon | September to November | 20-30°C | high | cool and wet |\n[/TABLE]\n\n[SECTION] Best Time To Visit [/SECTION]\n[CALLOUT] Best months: October to March. Why: The weather is cool and pleasant, making it ideal for sightseeing and outdoor activities. Avoid: May to August, as the weather is hot and humid, and the city experiences frequent power outages and water shortages. [/CALLOUT]\n\n[SECTION] Natural Highlights [/SECTION]\n- The Gomti River, which flows through the heart of the city and provides a source of water for irrigation and drinking.\n- The Lucknow Forest Division, which is a protected area that covers an area of over 100 square kilometers and is home to several species of trees and wildlife.\n- The Malwa Plateau, which is a relatively elevated region that is known for its scenic beauty and rich biodiversity.\n- The Lohia Park, which is a beautiful park that covers an area of over 30 acres and is known for its scenic beauty and peaceful atmosphere.\n- The Kukrail Forest, which is a protected area that covers an area of over 20 square kilometers and is home to several species of trees and wildlife.\n- The Dr. Ram Manohar Lohia Park, which is a beautiful park that covers an area of over 10 acres and is known for its scenic beauty and peaceful atmosphere.",
  "word_count": 932,
  "generated_date": "2026-03-03T04:34:23.143479"
}