{
  "entity": "Sweden",
  "entity_slug": "sweden",
  "iso_code": "SE",
  "continent": "europe",
  "angle": "moving-there",
  "title": "Moving to Sweden — Visas, Residency & Expat Guide",
  "content": "To move to Sweden, you will need to research and understand the various visa and residency options, relocation procedures, and cultural nuances that will help you navigate this beautiful and welcoming country.\n\n[SECTION] Why People Move to Sweden [/SECTION]\nSweden is a popular destination for expats, attracting people from all over the world with its stunning natural beauty, high standard of living, and strong economy. Many people move to Sweden for work, with the country being home to several multinational companies, including **IKEA**, **Ericsson**, and **H&M**. Others are drawn to the country's excellent education system, with several top-ranked universities, including the **University of Stockholm** and **Lund University**. The country's high quality of life, with good healthcare, low crime rates, and a strong social safety net, also makes it an attractive destination for families and retirees.\n\nExpats in Sweden come from a variety of backgrounds, with the largest groups coming from **Europe**, **Asia**, and **North America**. Many expats are drawn to the country's vibrant cities, including **Stockholm**, **Gothenburg**, and **Malmö**, which offer a wide range of cultural, entertainment, and recreational activities. Sweden is also known for its stunning natural beauty, with its **forests**, **lakes**, and **coastlines** offering plenty of opportunities for outdoor activities such as **hiking**, **skiing**, and **fishing**.\n\nOverall, Sweden offers a unique combination of natural beauty, economic stability, and high quality of life, making it an attractive destination for expats from all over the world. With its strong social safety net, excellent education system, and vibrant culture, Sweden is an ideal place to live, work, and raise a family.\n\n[SECTION] Visa & Residency Options [/SECTION]\n[TABLE]\n| Visa Type | Duration | Requirements | Cost (USD) | Path to PR? |\n| --- | --- | --- | --- | --- |\n| Tourist | Up to 90 days | Valid passport, proof of onward travel | $0 | No |\n| Work Visa | Up to 2 years, renewable | Job offer from Swedish employer, valid passport | $100-$300 | Yes |\n| Business/Investor | Up to 2 years, renewable | Business plan, proof of funds, valid passport | $500-$1,000 | Yes |\n| Retirement | Up to 5 years, renewable | Proof of pension or retirement income, valid passport | $100-$300 | No |\n| Student | Up to 1 year, renewable | Admission to Swedish university, valid passport | $100-$300 | No |\n| Digital Nomad | Up to 1 year, renewable | Proof of remote work, valid passport | $100-$300 | No |\n[/TABLE]\n\n[SECTION] Relocation Checklist [/SECTION]\n1. Research and understand the different visa and residency options available to you\n2. Gather all necessary documents, including a valid passport, birth certificate, and proof of income\n3. Apply for a visa or residence permit through the Swedish Migration Agency\n4. Find a place to live, either by renting an apartment or buying a house\n5. Open a Swedish bank account and transfer your money\n6. Register with the Swedish Tax Agency and obtain a tax identification number\n7. Find a job or start your own business\n8. Enroll in a Swedish language course to improve your language skills\n9. Get familiar with the Swedish healthcare system and register with a doctor\n10. Connect with other expats and join online communities to build a social network\n11. Learn about Swedish culture and customs to avoid cultural shock\n12. Plan for the cost of living in Sweden, including housing, food, and transportation\n\n[SECTION] Expat Communities [/SECTION]\n- **Stockholm** is home to a large and vibrant expat community, with many groups and organizations catering to different nationalities and interests\n- The **Expat Sweden** online forum is a great place to connect with other expats and get advice on living in Sweden\n- **Internations** is a global expat network with a large community in Sweden, offering events, groups, and activities for expats\n- **Meetup** is a great way to connect with other expats and like-minded individuals, with many groups focused on hobbies, sports, and cultural activities\n- **Facebook groups**, such as **Expats in Sweden** and **Sweden Expats**, offer a platform for expats to connect, ask questions, and share experiences\n\n[SECTION] Banking & Finances [/SECTION]\n- Opening a Swedish bank account is relatively straightforward, with many banks offering English-language services and online banking\n- **SEB**, **Handelsbanken**, and **Nordea** are some of the largest banks in Sweden, offering a range of services and products for expats\n- Money transfers can be done through banks, but online services like **TransferWise** and **PayPal** often offer better exchange rates and lower fees\n- Sweden is a cashless society, with many businesses and services only accepting card payments\n- Taxes in Sweden can be complex, so it's a good idea to consult with a tax professional or accountant to understand your obligations\n\n[SECTION] Challenges & Honest Advice [/SECTION]\n- **Language barriers** can be a challenge, especially outside of major cities, so it's a good idea to learn some Swedish to improve your experience\n- **Bureaucracy** can be slow and frustrating, so be patient and persistent when dealing with official paperwork and procedures\n- **Culture shock** is common, especially for those from non-European cultures, so be prepared to adapt to new customs and ways of life\n- **Weather** can be cold and dark, especially in the winter months, so be prepared to invest in warm clothing and lighting\n- **Cost of living** can be high, especially in major cities, so be prepared to budget carefully and plan for expenses\n- **Integration** can take time, so be patient and make an effort to connect with locals and learn about Swedish culture and customs\n\n[FACTBOX]\nKey: Population\nValue: 10,605,098\nKey: Area\nValue: 450,295 km²\nKey: Capital\nValue: Stockholm\n[/FACTBOX]\n\n[CALLOUT] Be prepared for the high cost of living in Sweden, especially in major cities like Stockholm and Gothenburg. Budget carefully and plan for expenses to ensure a smooth transition. [/CALLOUT]\n\n[RATING] label: 4/5\nSweden is a wonderful country to live in, with its stunning natural beauty, high standard of living, and strong economy. However, it can be challenging to adapt to the language, culture, and bureaucracy, so be prepared to be patient and persistent. With the right mindset and preparation, Sweden can be a fantastic place to call home.",
  "word_count": 1041,
  "generated_date": "2026-02-17T20:01:14.810121"
}