{
  "entity": "Zimbabwe",
  "entity_slug": "zimbabwe",
  "iso_code": "ZW",
  "continent": "africa",
  "angle": "cities-and-regions",
  "title": "Zimbabwe Cities & Regions Guide",
  "content": "Zimbabwe is divided into eight provinces, each with its unique character, and is home to several major cities, including the capital Harare, which offer a blend of cultural, economic, and tourist attractions.\n\n[FACTBOX]\nAdministrative Divisions: 8 provinces (Bulawayo, Harare, Manicaland, Mashonaland Central, Mashonaland East, Mashonaland West, Masvingo, Matabeleland South)\nLargest City: Harare, population over 1.6 million\nCapital: Harare\nNumber of Cities Over 1M: 1\n[/FACTBOX]\n\n[SECTION] How Zimbabwe Is Divided [/SECTION]\nZimbabwe is divided into eight provinces, each with its own provincial capital and a distinct character. These provinces are further divided into districts and then into wards, which are the smallest administrative units. The provinces are Bulawayo, Harare, Manicaland, Mashonaland Central, Mashonaland East, Mashonaland West, Masvingo, and Matabeleland South. This division helps in the effective governance and administration of the country, with each province having its own set of responsibilities and functions.\n\nThe administrative structure of Zimbabwe is designed to ensure that power is decentralized and that each region has a certain degree of autonomy. This helps in addressing the unique needs and challenges of each province, which can vary significantly. For example, the province of Matabeleland South has a strong focus on agriculture, while the province of Harare is more focused on commerce and industry. This division also helps in promoting regional development and reducing regional disparities.\n\n[SECTION] Major Cities [/SECTION]\n**Harare** (1.6 million)\nRole: capital city, economic hub, cultural center\nKnown For: Harare is known for its vibrant cultural scene, with numerous museums, galleries, and theaters, as well as its beautiful parks and gardens. The city is also home to a number of historic landmarks, including the National Archives and the Queen Victoria Museum.\nBest For: Harare is a great destination for visitors who are interested in history, culture, and entertainment.\n\n**Bulawayo** (650,000)\nRole: economic hub, cultural center, industrial center\nKnown For: Bulawayo is known for its rich history, with a number of historic landmarks, including the Bulawayo Railway Museum and the Natural History Museum. The city is also home to a number of cultural attractions, including the Bulawayo Theatre and the Bulawayo Art Gallery.\nBest For: Bulawayo is a great destination for visitors who are interested in history, culture, and industry.\n\n**Chitungwiza** (350,000)\nRole: satellite city, residential area, commercial center\nKnown For: Chitungwiza is known for its vibrant marketplaces, where visitors can find a wide range of goods, including traditional crafts, clothing, and food. The city is also home to a number of cultural attractions, including the Chitungwiza Arts Centre.\nBest For: Chitungwiza is a great destination for visitors who are interested in shopping, culture, and entertainment.\n\n**Mutare** (200,000)\nRole: economic hub, commercial center, tourist destination\nKnown For: Mutare is known for its stunning natural beauty, with a number of parks and reserves, including the Bunga Forest Botanical Reserve and the Vumba Botanical Gardens. The city is also home to a number of cultural attractions, including the Mutare Museum.\nBest For: Mutare is a great destination for visitors who are interested in nature, culture, and outdoor activities.\n\n**Gweru** (150,000)\nRole: economic hub, industrial center, educational center\nKnown For: Gweru is known for its rich history, with a number of historic landmarks, including the Gweru Museum and the Antelope Park. The city is also home to a number of cultural attractions, including the Gweru Theatre.\nBest For: Gweru is a great destination for visitors who are interested in history, culture, and education.\n\n[SECTION] Key Regions [/SECTION]\n[TABLE]\n| Region | Character | Known For | Major City |\n| --- | --- | --- | --- |\n| Mashonaland East | Agricultural, scenic | Tobacco farming, scenic landscapes | Marondera |\n| Mashonaland West | Agricultural, industrial | Mining, farming, scenic lakes | Chinhoyi |\n| Matabeleland North | Agricultural, tourist | Victoria Falls, wildlife reserves | Bulawayo |\n| Matabeleland South | Agricultural, rural | Cattle ranching, traditional villages | Gwanda |\n| Manicaland | Agricultural, scenic | Tea plantations, mountain scenery | Mutare |\n| Masvingo | Agricultural, historical | Great Zimbabwe ruins, scenic lakes | Masvingo |\n| Bulawayo | Industrial, cultural | Manufacturing, cultural attractions | Bulawayo |\n| Harare | Commercial, cultural | Business center, cultural attractions | Harare |\n[/TABLE]\n\n[SECTION] Regional Differences [/SECTION]\n- The regions of Zimbabwe differ significantly in terms of culture, with the Shona people dominating the northern regions and the Ndebele people dominating the southern regions.\n- The economy of each region also varies, with some regions being more focused on agriculture, while others are more focused on industry and commerce.\n- The climate of each region differs, with the eastern regions being more mountainous and cooler, while the western regions are more flat and hot.\n- The language spoken in each region also varies, with Shona being the dominant language in the north and Ndebele being the dominant language in the south.\n\n[SECTION] Getting Around [/SECTION]\nZimbabwe has a well-developed transportation network, with a number of domestic flights, trains, and buses connecting the major cities. The country is also home to a number of major highways, including the Harare-Bulawayo highway and the Harare-Mutare highway, which provide easy access to the different regions. However, driving conditions can be challenging, especially in rural areas, where the roads are often poorly maintained. Visitors can also use taxis and rental cars to get around, but these can be more expensive.\n\nThe train network in Zimbabwe is also well-developed, with a number of routes connecting the major cities. The trains are generally comfortable and affordable, but they can be slower than other forms of transportation. The bus network is also extensive, with a number of companies operating routes throughout the country. These buses are generally affordable and convenient, but they can be crowded and uncomfortable. Overall, visitors to Zimbabwe have a number of options for getting around, and the country's transportation network is generally well-developed and efficient.",
  "word_count": 977,
  "generated_date": "2026-02-18T04:56:15.693543"
}