{
  "entity": "Niger",
  "entity_slug": "niger",
  "iso_code": "NE",
  "continent": "africa",
  "angle": "top-things-to-do",
  "title": "Top Things to Do in Niger — Attractions & Experiences",
  "content": "When visiting Niger, some of the top things to do include exploring the stunning natural landscapes, experiencing the unique cultural heritage, and discovering the rich history of this West African country.\n\n[SECTION] Top Attractions [/SECTION]\n[TABLE]\n| Attraction | Location | Type | Why Visit |\n| --- | --- | --- | --- |\n| Air Mountains | Northern Niger | Mountain Range | Unique rock formations and breathtaking views |\n| Ayorou Game Reserve | Tillaberi Region | Wildlife Reserve | Diverse wildlife, including elephants, lions, and giraffes |\n| Tenere Tree | Ténéré Desert | Natural Landmark | Famous solitary tree in the desert, a symbol of resilience |\n| Niamey Museum | Niamey | Museum | Insight into Niger's history, culture, and natural environment |\n| Zinder Old Town | Zinder | Historical Site | Well-preserved traditional architecture and vibrant marketplace |\n| Ayorou Crocodile Farm | Tillaberi Region | Wildlife Farm | Conservation efforts and up-close encounters with crocodiles |\n| Termit Massif | Eastern Niger | Mountain Range | Scenic hiking trails and stunning vistas |\n| Wodaabe Gerewol Festival | In-Gall | Cultural Festival | Vibrant celebration of Wodaabe culture, music, and dance |\n| Koure Giraffe Reserve | Niamey Region | Wildlife Reserve | Home to the last remaining West African giraffes |\n| Agadez Mosque | Agadez | Historical Landmark | Ancient mosque and center of Islamic learning |\n[/TABLE]\n\n[SECTION] Unique Experiences [/SECTION]\n- Attend a traditional **Wodaabe** festival, known for its colorful costumes and energetic music\n- Take a **camel trek** through the Ténéré Desert, exploring the vast dunes and starry nights\n- Visit a **Tuareg** nomadic camp, learning about their customs and way of life\n- Explore the **ancient city** of Agadez, with its rich history and cultural significance\n- Experience the **Gerewol** festival, a celebration of beauty, music, and dance\n- Learn about **traditional medicine** and healing practices in Niger\n- Discover the **local crafts** and artisans, such as woodcarvings and textiles\n- Take a **stargazing tour**, gazing up at the incredible night sky in the Sahara Desert\n\n[SECTION] Outdoor & Nature [/SECTION]\n- **Air Mountains**, a mountain range with unique rock formations and stunning views\n- **Ayorou Game Reserve**, home to diverse wildlife, including elephants and lions\n- **Koure Giraffe Reserve**, a protected area for the last remaining West African giraffes\n- **Termit Massif**, a mountain range with scenic hiking trails and breathtaking vistas\n- **Niger River**, a major waterway with opportunities for boat tours and fishing\n- **Ténéré Desert**, a vast and stunning desert landscape, perfect for camel treks and exploration\n\n[SECTION] Cultural Experiences [/SECTION]\n- **Niamey Museum**, a museum showcasing Niger's history, culture, and natural environment\n- **Zinder Old Town**, a historic town with traditional architecture and vibrant marketplace\n- **Agadez Mosque**, an ancient mosque and center of Islamic learning\n- **Wodaabe Cultural Center**, a center dedicated to preserving Wodaabe culture and traditions\n- **Tuareg Music and Dance**, a performance showcasing the unique music and dance of the Tuareg people\n- **Local Markets**, vibrant marketplaces where visitors can experience the sights, sounds, and smells of Niger\n\n[SECTION] Hidden Gems [/SECTION]\n- **In-Gall**, a small town with a rich cultural heritage and stunning natural surroundings\n- **Tillaberi Region**, a region with diverse wildlife and natural beauty\n- **Koure**, a town known for its giraffe reserve and traditional crafts\n- **Abalak**, a town with a rich history and stunning natural surroundings\n- **Tassili**, a small village with a unique cultural heritage and stunning natural beauty\n\n[SECTION] Day Trips [/SECTION]\n- **Ayorou Game Reserve**, a day trip from Niamey to explore the diverse wildlife (distance: 200 km, travel time: 3 hours)\n- **Zinder Old Town**, a day trip from Niamey to explore the historic town and vibrant marketplace (distance: 900 km, travel time: 12 hours)\n- **Agadez**, a day trip from Niamey to explore the ancient city and its cultural significance (distance: 900 km, travel time: 12 hours)\n- **Koure Giraffe Reserve**, a day trip from Niamey to visit the giraffe reserve and learn about conservation efforts (distance: 100 km, travel time: 2 hours)\n- **In-Gall**, a day trip from Agadez to experience the Wodaabe culture and attend a traditional festival (distance: 150 km, travel time: 3 hours)\n\n[SECTION] Planning Tips [/SECTION]\n[CALLOUT] Suggested itineraries: \n3-day itinerary: Explore Niamey, visit the Niamey Museum, and take a day trip to the Ayorou Game Reserve.\n7-day itinerary: Visit the Air Mountains, Zinder Old Town, and Agadez, with a day trip to the Koure Giraffe Reserve.\n14-day itinerary: Take a camel trek through the Ténéré Desert, visit the Wodaabe Cultural Center, and explore the Tillaberi Region.\nKey tips: book accommodations and transportation in advance, prioritize cultural experiences and outdoor activities, and be respectful of local customs and traditions. [/CALLOUT]",
  "word_count": 799,
  "generated_date": "2026-02-17T18:49:10.300789"
}